doodleverse_utils/__init__.py
doodleverse_utils/_version.py
doodleverse_utils/imports.py
doodleverse_utils/make_mndwi_4pred.py
doodleverse_utils/make_mndwi_dataset.py
doodleverse_utils/make_ndwi_4pred.py
doodleverse_utils/make_ndwi_dataset.py
doodleverse_utils/merge_nd_inputs4pred.py
doodleverse_utils/model_imports.py
doodleverse_utils/model_metrics.py
doodleverse_utils/prediction_imports.py
doodleverse_utils/vggjson2mask.py
doodleverse_utils-0.0.39.dist-info/LICENSE
doodleverse_utils-0.0.39.dist-info/METADATA
doodleverse_utils-0.0.39.dist-info/WHEEL
doodleverse_utils-0.0.39.dist-info/top_level.txt
doodleverse_utils-0.0.39.dist-info/RECORD
