Metadata-Version: 2.1
Name: doodleverse-utils
Version: 0.0.39
Summary: Imports into the Doodleverse
Author: Daniel Buscombe
Author-email: dbuscombe@gmail.email
Classifier: Programming Language :: Python :: 3
Classifier: License :: OSI Approved :: MIT License
Classifier: Operating System :: OS Independent
Requires-Python: >=3.6
License-File: LICENSE
Requires-Dist: versioneer
